{
  "VT": {
    "當前價格": 139.52,
    "更新時間": "2026-03-13",
    "H_1M": 149.07,
    "H_Date_1M": "2026-02-26",
    "From_H_%_1M": -6.41,
    "L_1M": 139.35,
    "L_Date_1M": "2026-03-13",
    "From_L_%_1M": 0.13,
    "Range_%_1M": 6.98,
    "H_3M": 149.07,
    "H_Date_3M": "2026-02-26",
    "From_H_%_3M": -6.41,
    "L_3M": 138.22,
    "L_Date_3M": "2025-12-17",
    "From_L_%_3M": 0.94,
    "Range_%_3M": 7.85,
    "H_6M": 149.07,
    "H_Date_6M": "2026-02-26",
    "From_H_%_6M": -6.41,
    "L_6M": 133.41,
    "L_Date_6M": "2025-11-21",
    "From_L_%_6M": 4.58,
    "Range_%_6M": 11.74,
    "H_1Y": 149.07,
    "H_Date_1Y": "2026-02-26",
    "From_H_%_1Y": -6.41,
    "L_1Y": 99.27,
    "L_Date_1Y": "2025-04-07",
    "From_L_%_1Y": 40.55,
    "Range_%_1Y": 50.17,
    "H_YTD": 149.07,
    "H_Date_YTD": "2026-02-26",
    "From_H_%_YTD": -6.41,
    "L_YTD": 139.35,
    "L_Date_YTD": "2026-03-13",
    "From_L_%_YTD": 0.13,
    "Range_%_YTD": 6.98,
    "H_3Y": 149.07,
    "H_Date_3Y": "2026-02-26",
    "From_H_%_3Y": -6.41,
    "L_3Y": 82.13,
    "L_Date_3Y": "2023-03-17",
    "From_L_%_3Y": 69.87,
    "Range_%_3Y": 81.5
  },
  "VOO": {
    "當前價格": 609.09,
    "更新時間": "2026-03-13",
    "H_1M": 639.52,
    "H_Date_1M": "2026-02-12",
    "From_H_%_1M": -4.76,
    "L_1M": 608.26,
    "L_Date_1M": "2026-03-13",
    "From_L_%_1M": 0.14,
    "Range_%_1M": 5.14,
    "H_3M": 641.81,
    "H_Date_3M": "2026-01-28",
    "From_H_%_3M": -5.1,
    "L_3M": 608.26,
    "L_Date_3M": "2026-03-13",
    "From_L_%_3M": 0.14,
    "Range_%_3M": 5.52,
    "H_6M": 641.81,
    "H_Date_6M": "2026-01-28",
    "From_H_%_6M": -5.1,
    "L_6M": 596.69,
    "L_Date_6M": "2025-11-21",
    "From_L_%_6M": 2.08,
    "Range_%_6M": 7.56,
    "H_1Y": 641.81,
    "H_Date_1Y": "2026-01-28",
    "From_H_%_1Y": -5.1,
    "L_1Y": 438.94,
    "L_Date_1Y": "2025-04-07",
    "From_L_%_1Y": 38.77,
    "Range_%_1Y": 46.22,
    "H_YTD": 641.81,
    "H_Date_YTD": "2026-01-28",
    "From_H_%_YTD": -5.1,
    "L_YTD": 608.26,
    "L_Date_YTD": "2026-03-13",
    "From_L_%_YTD": 0.14,
    "Range_%_YTD": 5.52,
    "H_3Y": 641.81,
    "H_Date_3Y": "2026-01-28",
    "From_H_%_3Y": -5.1,
    "L_3Y": 343.94,
    "L_Date_3Y": "2023-03-17",
    "From_L_%_3Y": 77.09,
    "Range_%_3Y": 86.61
  },
  "VTI": {
    "當前價格": 326.13,
    "更新時間": "2026-03-13",
    "H_1M": 343.33,
    "H_Date_1M": "2026-02-12",
    "From_H_%_1M": -5.01,
    "L_1M": 325.67,
    "L_Date_1M": "2026-03-13",
    "From_L_%_1M": 0.14,
    "Range_%_1M": 5.42,
    "H_3M": 344.42,
    "H_Date_3M": "2026-01-28",
    "From_H_%_3M": -5.31,
    "L_3M": 325.67,
    "L_Date_3M": "2026-03-13",
    "From_L_%_3M": 0.14,
    "Range_%_3M": 5.76,
    "H_6M": 344.42,
    "H_Date_6M": "2026-01-28",
    "From_H_%_6M": -5.31,
    "L_6M": 318.54,
    "L_Date_6M": "2025-11-21",
    "From_L_%_6M": 2.38,
    "Range_%_6M": 8.13,
    "H_1Y": 344.42,
    "H_Date_1Y": "2026-01-28",
    "From_H_%_1Y": -5.31,
    "L_1Y": 234.39,
    "L_Date_1Y": "2025-04-07",
    "From_L_%_1Y": 39.14,
    "Range_%_1Y": 46.94,
    "H_YTD": 344.42,
    "H_Date_YTD": "2026-01-28",
    "From_H_%_YTD": -5.31,
    "L_YTD": 325.67,
    "L_Date_YTD": "2026-03-13",
    "From_L_%_YTD": 0.14,
    "Range_%_YTD": 5.76,
    "H_3Y": 344.42,
    "H_Date_3Y": "2026-01-28",
    "From_H_%_3Y": -5.31,
    "L_3Y": 186.53,
    "L_Date_3Y": "2023-03-17",
    "From_L_%_3Y": 74.84,
    "Range_%_3Y": 84.65
  },
  "SOXX": {
    "當前價格": 331.32,
    "更新時間": "2026-03-13",
    "H_1M": 368.82,
    "H_Date_1M": "2026-02-25",
    "From_H_%_1M": -10.17,
    "L_1M": 316.22,
    "L_Date_1M": "2026-03-09",
    "From_L_%_1M": 4.78,
    "Range_%_1M": 16.63,
    "H_3M": 368.82,
    "H_Date_3M": "2026-02-25",
    "From_H_%_3M": -10.17,
    "L_3M": 284.43,
    "L_Date_3M": "2025-12-17",
    "From_L_%_3M": 16.49,
    "Range_%_3M": 29.67,
    "H_6M": 368.82,
    "H_Date_6M": "2026-02-25",
    "From_H_%_6M": -10.17,
    "L_6M": 253.26,
    "L_Date_6M": "2025-09-12",
    "From_L_%_6M": 30.82,
    "Range_%_6M": 45.63,
    "H_1Y": 368.82,
    "H_Date_1Y": "2026-02-25",
    "From_H_%_1Y": -10.17,
    "L_1Y": 147.46,
    "L_Date_1Y": "2025-04-07",
    "From_L_%_1Y": 124.69,
    "Range_%_1Y": 150.12,
    "H_YTD": 368.82,
    "H_Date_YTD": "2026-02-25",
    "From_H_%_YTD": -10.17,
    "L_YTD": 308.56,
    "L_Date_YTD": "2026-01-02",
    "From_L_%_YTD": 7.38,
    "Range_%_YTD": 19.53,
    "H_3Y": 368.82,
    "H_Date_3Y": "2026-02-25",
    "From_H_%_3Y": -10.17,
    "L_3Y": 128.9,
    "L_Date_3Y": "2023-04-27",
    "From_L_%_3Y": 157.04,
    "Range_%_3Y": 186.13
  }
}